astrolore/__init__.py
astrolore/aladin_test.py
astrolore/dataset.py
astrolore/gui.py
astrolore/gui_demo.py
astrolore/tkwindow.py
astrolore/data/__init__.py
astrolore/data/background.png
astrolore/data/scifi_dataset.csv
astrolore-1.0.0.dist-info/licenses/LICENSE
astrolore-1.0.0.dist-info/METADATA
astrolore-1.0.0.dist-info/WHEEL
astrolore-1.0.0.dist-info/top_level.txt
astrolore-1.0.0.dist-info/RECORD
