Metadata-Version: 2.4
Name: astrolore
Version: 1.0.0
Summary: package for finding nearest source in sci-fi
Author-email: Joe Adamo <jadamo@arizona.edu>, Kayvon Sharifi <ksharifi1@gsu.edu>, Isabele Souza Vitorio <ivitorio@umich.edu>, Arnab Lahiry <alahiry@ics.forth.gr>
Project-URL: Homepage, https://github.com/sharifikayvon/astrolore
Requires-Python: >=3.9
License-File: LICENSE
Requires-Dist: pandas
Requires-Dist: astropy
Requires-Dist: numpy
Requires-Dist: build
Requires-Dist: setuptools
Requires-Dist: pywebview
Requires-Dist: matplotlib
Dynamic: license-file
